pymono/__init__.py
pymono/types.py
pymono/util.py
pymono/version.py
PyMonoLib-0.3.2.dist-info/METADATA
PyMonoLib-0.3.2.dist-info/WHEEL
PyMonoLib-0.3.2.dist-info/top_level.txt
PyMonoLib-0.3.2.dist-info/RECORD
