Metadata-Version: 2.1
Name: PyMonoLib
Version: 0.3.2
Summary: Monobank Python wrapper
Home-page: https://github.com/makisukurisu/py-mono-api
Author: makisukurisu
Author-email: 667strets@gmail.com
License: GPL2
Keywords: telegram api tools
Platform: UNKNOWN
Classifier: Development Status :: 5 - Production/Stable
Classifier: Programming Language :: Python :: 3
Classifier: Environment :: Console
Classifier: License :: OSI Approved :: GNU General Public License v2 (GPLv2)
Requires-Dist: requests
Provides-Extra: json
Requires-Dist: ujson ; extra == 'json'
